{"headline": "Aid Groups Seek Access To Refugees In Ethiopia", "webPublicationDate": "2020-11-17T23:34:37+0000", "text": "ADDIS ABABA, Ethiopia \u2014 Even before fighting started in November between the Ethiopian government and powerful military forces in the country\u2019s northern region of Tigray, the area was home to as many as 200,000 refugees and displaced people, according to United Nations agencies.", "snippet": "Blocked roads, cut communications, intensifying combat: Aid groups say they stand ready to help people caught in the Ethiopian fighting, if only they could.", "type_of_material": "News", "news_desk": "Foreign"}