{"headline": "The Voters Lining Up Before Dawn to Have Their Say", "webPublicationDate": "2020-11-03T12:55:46+0000", "text": "Although tens of millions of Americans chose to cast their ballots early this year, voting in person on Election Day still held a certain appeal for the people lining up early Tuesday \u2014 whether because it had become tradition or because they just could not sleep.", "snippet": "Voters lined up before dawn in many places for a chance to cast their ballot.", "type_of_material": "News", "news_desk": "Politics"}