{"headline": "Truce Eases Fighting  Over Armenian Enclave", "webPublicationDate": "2020-10-10T14:50:30+0000", "text": "GORIS, Armenia \u2014 Fierce fighting over a breakaway Armenian enclave in Azerbaijan partly subsided on Saturday after a cease-fire took effect. But there was little expectation of a durable peace two weeks into the most violent conflict that the volatile region has seen in decades.", "snippet": "The Armenian Defense Ministry said most of the front line was \u201crelatively calm.\u201d But renewed shelling was reported at night.", "type_of_material": "News", "news_desk": "Foreign"}