{"headline": "A Frayed Bond Between Biden And the Police", "webPublicationDate": "2020-10-24T15:13:34+0000", "text": "Bill Johnson knew, before he reached out to Joseph R. Biden Jr.\u2019s campaign last spring, that things had changed between the former vice president and the nation\u2019s police unions. A once-close alliance had frayed amid clashes over police brutality and racism in the justice system. Still, Mr. Johnson, the executive director of the National Association of Police Organizations, invited Mr. Biden to address the group as it weighed its 2020 endorsement.", "snippet": "His proposed solution to addressing both urgent calls for police reform and animosity from law enforcement toward Democrats is one he\u2019s long relied on: He\u2019ll just get everyone in the same room.", "type_of_material": "News", "news_desk": "Politics"}