{"headline": null, "webPublicationDate": "2020-11-04T02:45:53+0000", "text": "Madison Cawthorn won North Carolina\u2019s 11th Congressional District on Tuesday, defeating the former Air Force colonel Moe Davis and keeping the conservative seat in Republican hands after a race that became unexpectedly competitive when Mr. Cawthorn was accused of racism and sexual misconduct.", "snippet": "The 25-year-old kept the solidly conservative seat in G.O.P. hands after his race had become unexpectedly competitive when he was accused of sexual misconduct and racism.", "type_of_material": "News", "news_desk": "Politics"}