{"headline": "A Trump Victory? Palestinians Would Rather Not Think About It", "webPublicationDate": "2020-10-28T17:48:50+0000", "text": "RAMALLAH, West Bank \u2014 The Palestinians are counting on a Trump defeat next Tuesday. They don\u2019t even want to think about Plan B.", "snippet": "A Biden victory could bring economic relief for Palestinians and friendlier relations with Washington, though not a return to 2016. A Trump win? They\u2019d rather not think about it.", "type_of_material": "News", "news_desk": "Foreign"}