{"headline": "\u2018Touching Discovery\u2019: Victims of Vesuvius Eruption", "webPublicationDate": "2020-11-21T15:29:30+0000", "text": "ROME \u2014 Excavations at a suburban villa outside ancient Pompeii this month have recovered the remains of two original dwellers frozen in time by an eruption of Mount Vesuvius one fateful morning nearly 2,000 years ago.", "snippet": "Archaeologists tentatively identified the pair as a wealthy landowner and a younger enslaved person, both of whom were killed in the 79 A.D. eruption.", "type_of_material": "News", "news_desk": "Foreign"}