{"headline": "With Senate at Stake in Georgia, Progressives Focus on \u2018Bigger Picture\u2019", "webPublicationDate": "2020-12-01T10:00:29+0000", "text": "Neither Jon Ossoff nor the Rev. Raphael Warnock has endorsed the Green New Deal. But that hasn\u2019t stopped the Sunrise Movement, the activist climate group that champions the sweeping climate change plan, from mobilizing in force for the two Georgia Democrats in their high-stakes runoff races for Senate seats.", "snippet": "The two Democrats running in Georgia don\u2019t share the far-reaching policy goals of their party\u2019s left flank, but progressives are still trying to help them \u2014 with modified messages.", "type_of_material": "News", "news_desk": "Politics"}